docs/Makefile
docs/authors.md
docs/changelog.md
docs/conf.py
docs/contributing.md
docs/index.md
docs/license.md
docs/postprocess.py
docs/readme.md
docs/requirements.txt
docs/_static/.gitignore
docs/_static/utils/equiadapt_cat.jpeg
equiadapt/__init__.py
equiadapt/py.typed
equiadapt/common/__init__.py
equiadapt/common/basecanonicalization.py
equiadapt/common/utils.py
equiadapt/images/__init__.py
equiadapt/images/utils.py
equiadapt/images/canonicalization/__init__.py
equiadapt/images/canonicalization/continuous_group.py
equiadapt/images/canonicalization/discrete_group.py
equiadapt/images/canonicalization_networks/__init__.py
equiadapt/images/canonicalization_networks/custom_equivariant_networks.py
equiadapt/images/canonicalization_networks/custom_group_equivariant_layers.py
equiadapt/images/canonicalization_networks/custom_nonequivariant_networks.py
equiadapt/images/canonicalization_networks/escnn_networks.py
equiadapt/nbody/__init__.py
equiadapt/nbody/canonicalization/__init__.py
equiadapt/nbody/canonicalization/euclidean_group.py
equiadapt/nbody/canonicalization_networks/__init__.py
equiadapt/nbody/canonicalization_networks/custom_equivariant_networks.py
equiadapt/nbody/canonicalization_networks/custom_group_equivariant_layers.py
equiadapt/pointcloud/__init__.py
equiadapt/pointcloud/canonicalization/__init__.py
equiadapt/pointcloud/canonicalization/continuous_group.py
equiadapt/pointcloud/canonicalization_networks/__init__.py
equiadapt/pointcloud/canonicalization_networks/equivariant_networks.py
equiadapt/pointcloud/canonicalization_networks/vector_neuron_layers.py
examples/__init__.py
examples/images/__init__.py
examples/images/classification/README.md
examples/images/classification/__init__.py
examples/images/classification/inference_utils.py
examples/images/classification/model.py
examples/images/classification/model_utils.py
examples/images/classification/train.py
examples/images/classification/train_utils.py
examples/images/classification/configs/__init__.py
equiadapt-0.1.2.dist-info/LICENSE
equiadapt-0.1.2.dist-info/METADATA
equiadapt-0.1.2.dist-info/WHEEL
equiadapt-0.1.2.dist-info/top_level.txt
equiadapt-0.1.2.dist-info/RECORD
