Metadata-Version: 2.1
Name: equiadapt
Version: 0.1.2
Summary: Library to make any existing neural network architecture equivariant
Home-page: https://github.com/arnab39/EquivariantAdaptation/
Author: Arnab Mondal, Siba Smarak Panigrahi
Author-email: arnab.mondal@mila.quebec, siba-smarak.panigrahi@mila.quebec
License: MIT
Project-URL: Tracker, https://github.com/arnab39/EquivariantAdaptation/issues
Project-URL: Source, https://github.com/arnab39/EquivariantAdaptation/
Project-URL: Documentation, https://equiadapt.readthedocs.io/en/latest/
Platform: Linux
Classifier: Programming Language :: Python :: 3
Classifier: License :: OSI Approved :: MIT License
Classifier: Operating System :: OS Independent
Requires-Python: >=3.7
License-File: LICENSE
Requires-Dist: torch
Requires-Dist: numpy
Requires-Dist: torchvision
Requires-Dist: kornia
Requires-Dist: e2cnn
Requires-Dist: hydra-core
Provides-Extra: testing
Requires-Dist: setuptools ; extra == 'testing'
Requires-Dist: pytest ; extra == 'testing'
Requires-Dist: pytest-cov ; extra == 'testing'
